sacremoses/__init__.py
sacremoses/__main__.py
sacremoses/chinese.py
sacremoses/cli.py
sacremoses/corpus.py
sacremoses/indic.py
sacremoses/normalize.py
sacremoses/sent_tokenize.py
sacremoses/subwords.py
sacremoses/tokenize.py
sacremoses/truecase.py
sacremoses/util.py
sacremoses/data/nonbreaking_prefixes/nonbreaking_prefix.as
sacremoses/data/nonbreaking_prefixes/nonbreaking_prefix.bn
sacremoses/data/nonbreaking_prefixes/nonbreaking_prefix.ca
sacremoses/data/nonbreaking_prefixes/nonbreaking_prefix.cs
sacremoses/data/nonbreaking_prefixes/nonbreaking_prefix.de
sacremoses/data/nonbreaking_prefixes/nonbreaking_prefix.el
sacremoses/data/nonbreaking_prefixes/nonbreaking_prefix.en
sacremoses/data/nonbreaking_prefixes/nonbreaking_prefix.es
sacremoses/data/nonbreaking_prefixes/nonbreaking_prefix.et
sacremoses/data/nonbreaking_prefixes/nonbreaking_prefix.fi
sacremoses/data/nonbreaking_prefixes/nonbreaking_prefix.fr
sacremoses/data/nonbreaking_prefixes/nonbreaking_prefix.ga
sacremoses/data/nonbreaking_prefixes/nonbreaking_prefix.gu
sacremoses/data/nonbreaking_prefixes/nonbreaking_prefix.hi
sacremoses/data/nonbreaking_prefixes/nonbreaking_prefix.hu
sacremoses/data/nonbreaking_prefixes/nonbreaking_prefix.is
sacremoses/data/nonbreaking_prefixes/nonbreaking_prefix.it
sacremoses/data/nonbreaking_prefixes/nonbreaking_prefix.kn
sacremoses/data/nonbreaking_prefixes/nonbreaking_prefix.lt
sacremoses/data/nonbreaking_prefixes/nonbreaking_prefix.lv
sacremoses/data/nonbreaking_prefixes/nonbreaking_prefix.ml
sacremoses/data/nonbreaking_prefixes/nonbreaking_prefix.mni
sacremoses/data/nonbreaking_prefixes/nonbreaking_prefix.mr
sacremoses/data/nonbreaking_prefixes/nonbreaking_prefix.nl
sacremoses/data/nonbreaking_prefixes/nonbreaking_prefix.or
sacremoses/data/nonbreaking_prefixes/nonbreaking_prefix.pa
sacremoses/data/nonbreaking_prefixes/nonbreaking_prefix.pl
sacremoses/data/nonbreaking_prefixes/nonbreaking_prefix.pt
sacremoses/data/nonbreaking_prefixes/nonbreaking_prefix.ro
sacremoses-0.1.0.dist-info/LICENSE
sacremoses-0.1.0.dist-info/METADATA
sacremoses-0.1.0.dist-info/WHEEL
sacremoses-0.1.0.dist-info/entry_points.txt
sacremoses-0.1.0.dist-info/top_level.txt
sacremoses-0.1.0.dist-info/RECORD
