Metadata-Version: 2.1
Name: sacremoses
Version: 0.1.0
Summary: SacreMoses
Home-page: https://github.com/hplt-project/sacremoses
Author: 
Classifier: Programming Language :: Python :: 3
Classifier: License :: OSI Approved :: MIT License
Classifier: Operating System :: OS Independent
Requires-Python: >=3.8
License-File: LICENSE
Requires-Dist: regex
Requires-Dist: click
Requires-Dist: joblib
Requires-Dist: tqdm
